odoo/addons/account_analytic_required/README.rst
odoo/addons/account_analytic_required/__init__.py
odoo/addons/account_analytic_required/__manifest__.py
odoo/addons/account_analytic_required/i18n/account_analytic_required.pot
odoo/addons/account_analytic_required/i18n/ar.po
odoo/addons/account_analytic_required/i18n/ca.po
odoo/addons/account_analytic_required/i18n/de.po
odoo/addons/account_analytic_required/i18n/es.po
odoo/addons/account_analytic_required/i18n/es_CO.po
odoo/addons/account_analytic_required/i18n/fr.po
odoo/addons/account_analytic_required/i18n/hr_HR.po
odoo/addons/account_analytic_required/i18n/nl.po
odoo/addons/account_analytic_required/i18n/pt_BR.po
odoo/addons/account_analytic_required/i18n/zh_CN.po
odoo/addons/account_analytic_required/migrations/13.0.2.0.0/post-migrate.py
odoo/addons/account_analytic_required/models/__init__.py
odoo/addons/account_analytic_required/models/account.py
odoo/addons/account_analytic_required/readme/CONFIGURE.rst
odoo/addons/account_analytic_required/readme/CONTRIBUTORS.rst
odoo/addons/account_analytic_required/readme/DESCRIPTION.rst
odoo/addons/account_analytic_required/readme/USAGE.rst
odoo/addons/account_analytic_required/static/description/icon.png
odoo/addons/account_analytic_required/static/description/index.html
odoo/addons/account_analytic_required/tests/__init__.py
odoo/addons/account_analytic_required/tests/test_account_analytic_required.py
odoo/addons/account_analytic_required/views/account.xml
odoo13_addon_account_analytic_required-13.0.2.0.2.dist-info/METADATA
odoo13_addon_account_analytic_required-13.0.2.0.2.dist-info/WHEEL
odoo13_addon_account_analytic_required-13.0.2.0.2.dist-info/top_level.txt
odoo13_addon_account_analytic_required-13.0.2.0.2.dist-info/RECORD
